lakery/__init__.py
lakery/py.typed
lakery-0.0.1a1.dist-info/METADATA
lakery-0.0.1a1.dist-info/WHEEL
lakery-0.0.1a1.dist-info/licenses/LICENSE.txt
lakery-0.0.1a1.dist-info/RECORD
