Metadata-Version: 2.4
Name: lakery
Version: 0.0.1a1
Summary: A data lake creation tool for Python.
Project-URL: Source, https://github.com/rmorshea/lakery
Author-email: Ryan Morshead <ryan.morshead@gmail.com>
License: MIT License
License-File: LICENSE.txt
Classifier: Development Status :: 4 - Beta
Classifier: Programming Language :: Python
Requires-Python: >=3.11
Requires-Dist: anyio<5,>=4.6.2
Requires-Dist: anysync<1,>=0.3.1
Requires-Dist: pybooster<1,>=0.0.7
Requires-Dist: sqlalchemy[asyncio]<3,>=2.0.36
Requires-Dist: tenacity<10,>=9.0.0
Requires-Dist: typing-extensions<5,>=4
Provides-Extra: all
Requires-Dist: azure-storage-blob<13,>=12; extra == 'all'
Requires-Dist: boto3<2,>=1; extra == 'all'
Requires-Dist: google-cloud-storage<3,>=2; extra == 'all'
Requires-Dist: msgpack<2,>=1; extra == 'all'
Requires-Dist: numpy<3,>=2; extra == 'all'
Requires-Dist: pandas<3,>=2; extra == 'all'
Requires-Dist: plotly<6,>=5; extra == 'all'
Requires-Dist: polars>=1.18.0; extra == 'all'
Requires-Dist: pyarrow<19,>=18; extra == 'all'
Requires-Dist: pydantic<3,>=2; extra == 'all'
Provides-Extra: aws
Requires-Dist: boto3<2,>=1; extra == 'aws'
Provides-Extra: azure
Requires-Dist: azure-storage-blob<13,>=12; extra == 'azure'
Provides-Extra: google
Requires-Dist: google-cloud-storage<3,>=2; extra == 'google'
Provides-Extra: msgpack
Requires-Dist: msgpack<2,>=1; extra == 'msgpack'
Provides-Extra: numpy
Requires-Dist: numpy<3,>=2; extra == 'numpy'
Provides-Extra: pandas
Requires-Dist: pandas<3,>=2; extra == 'pandas'
Requires-Dist: pyarrow<19,>=18; extra == 'pandas'
Provides-Extra: plotly
Requires-Dist: plotly<6,>=5; extra == 'plotly'
Provides-Extra: polars
Requires-Dist: polars>=1.18.0; extra == 'polars'
Provides-Extra: pyarrow
Requires-Dist: pyarrow<19,>=18; extra == 'pyarrow'
Provides-Extra: pydantic
Requires-Dist: pydantic<3,>=2; extra == 'pydantic'
